calculator_wxb/__init__.py
calculator_wxb/operations.py
calculator_wxb-1.0.0.dist-info/LICENSE
calculator_wxb-1.0.0.dist-info/METADATA
calculator_wxb-1.0.0.dist-info/WHEEL
calculator_wxb-1.0.0.dist-info/entry_points.txt
calculator_wxb-1.0.0.dist-info/top_level.txt
calculator_wxb-1.0.0.dist-info/RECORD
